clock.v
// real time stop watch clock
module clock(
	input clk,rst,
	output reg [4:0]hrs,
	output reg [5:0]mins,
	output reg [5:0]sec);
always @(posedge clk or posedge rst) begin
if(~rst)begin
	hrs<=0;
	mins<=0;
	sec<=0;
end 

else begin 

if(sec==59)begin

sec<=0;  // sec=0

if(mins==59)begin

mins<=0;  // minute =0

if(hrs==23)

hrs<=0;  // hours=0

else

hrs<=hrs+1;

end 

else begin

mins<=mins+1;

end 

end else begin

sec<=sec+1; 

end

end
end
endmodule 


// test bench 

module tb;

reg clk;
reg rst;
wire [4:0]hrs;
wire [5:0]mins;
wire [5:0]sec;

clock dut (.*);

always #1 clk =~clk;

initial begin 
$monitor ("  hours  = %d   ::    minute  = %d   ::    second =%d ",hrs,mins,sec);
clk=1'b0;
rst =0;
#20 rst =1;
#172800 rst=0;
#120 $finish;
end

initial begin

$dumpfile("dump.vcd");
$dumpvars(0,tb);

end
endmodule

dump.vcd
$date
	Sat Apr 19 15:18:46 2025
$end
$version
	Icarus Verilog
$end
$timescale
	1s
$end
$scope module tb $end
$var wire 6 ! sec [5:0] $end
$var wire 6 " mins [5:0] $end
$var wire 5 # hrs [4:0] $end
$var reg 1 $ clk $end
$var reg 1 % rst $end
$scope module dut $end
$var wire 1 $ clk $end
$var wire 1 % rst $end
$var reg 5 & hrs [4:0] $end
$var reg 6 ' mins [5:0] $end
$var reg 6 ( sec [5:0] $end
$upscope $end
$upscope $end
$enddefinitions $end
$comment Show the parameter values. $end
$dumpall
$end
#0
$dumpvars
bx (
bx '
bx &
0%
0$
bx #
bx "
bx !
$end
#1
b0 !
b0 (
b0 "
b0 '
b0 #
b0 &
1$
#2
0$
#3
1$
#4
0$
#5
1$
#6
0$
#7
1$
#8
0$
#9
1$
#10
0$
#11
1$
#12
0$
#13
1$
#14
0$
#15
1$
#16
0$
#17
1$
#18
0$
#19
1$
#20
b1 !
b1 (
0$
1%
#21
b10 !
b10 (
1$
#22
0$
#23
b11 !
b11 (
1$
#24
0$
#25
b100 !
b100 (
1$
#26
0$
#27
b101 !
b101 (
1$
#28
0$
#29
b110 !
b110 (
1$
#30
0$
#31
b111 !
b111 (
1$
#32
0$
#33
b1000 !
b1000 (
1$
#34
0$
#35
b1001 !
b1001 (
1$
#36
0$
#37
b1010 !
b1010 (
1$
#38
0$
#39
b1011 !
b1011 (
1$
#40
0$
#41
b1100 !
b1100 (
1$
#42
0$
#43
b1101 !
b1101 (
1$
#44
0$
#45
b1110 !
b1110 (
1$
#46
0$
#47
b1111 !
b1111 (
1$
#48
0$
#49
b10000 !
b10000 (
1$
#50
0$
#51
b10001 !
b10001 (
1$
#52
0$
#53
b10010 !
b10010 (
1$
#54
0$
#55
b10011 !
b10011 (
1$
#56
0$
#57
b10100 !
b10100 (
1$
#58
0$
#59
b10101 !
b10101 (
1$
#60
0$
#61
b10110 !
b10110 (
1$
#62
0$
#63
b10111 !
b10111 (
1$
#64
0$
#65
b11000 !
b11000 (
1$
#66
0$
#67
b11001 !
b11001 (
1$
#68
0$
#69
b11010 !
b11010 (
1$
#70
0$
#71
b11011 !
b11011 (
1$
#72
0$
#73
b11100 !
b11100 (
1$
#74
0$
#75
b11101 !
b11101 (
1$
#76
0$
#77
b11110 !
b11110 (
1$
#78
0$
#79
b11111 !
b11111 (
1$
#80
0$
#81
b100000 !
b100000 (
1$
#82
0$
#83
b100001 !
b100001 (
1$
#84
0$
#85
b100010 !
b100010 (
1$
#86
0$
#87
b100011 !
b100011 (
1$
#88
0$
#89
b100100 !
b100100 (
1$
#90
0$
#91
b100101 !
b100101 (
1$
#92
0$
#93
b100110 !
b100110 (
1$
#94
0$
#95
b100111 !
b100111 (
1$
#96
0$
#97
b101000 !
b101000 (
1$
#98
0$
#99
b101001 !
b101001 (
1$
#100
0$
#101
b101010 !
b101010 (
1$
#102
0$
#103
b101011 !
b101011 (
1$
#104
0$
#105
b101100 !
b101100 (
1$
#106
0$
#107
b101101 !
b101101 (
1$
#108
0$
#109
b101110 !
b101110 (
1$
#110
0$
#111
b101111 !
b101111 (
1$
#112
0$
#113
b110000 !
b110000 (
1$
#114
0$
#115
b110001 !
b110001 (
1$
#116
0$
#117
b110010 !
b110010 (
1$
#118
0$
#119
b110011 !
b110011 (
1$
#120
0$
#121
b110100 !
b110100 (
1$
#122
0$
#123
b110101 !
b110101 (
1$
#124
0$
#125
b110110 !
b110110 (
1$
#126
0$
#127
b110111 !
b110111 (
1$
#128
0$
#129
b111000 !
b111000 (
1$
#130
0$
#131
b111001 !
b111001 (
1$
#132
0$
#133
b111010 !
b111010 (
1$
#134
0$
#135
b111011 !
b111011 (
1$
#136
0$
#137
b1 "
b1 '
b0 !
b0 (
1$
#138
0$
#139
b1 !
b1 (
1$
#140
0$
#141
b10 !
b10 (
1$
#142
0$
#143
b11 !
b11 (
1$
#144
0$
#145
b100 !
b100 (
1$
#146
0$
#147
b101 !
b101 (
1$
#148
0$
#149
b110 !
b110 (
1$
#150
0$
#151
b111 !
b111 (
1$
#152
0$
#153
b1000 !
b1000 (
1$
#154
0$
#155
b1001 !
b1001 (
1$
#156
0$
#157
b1010 !
b1010 (
1$
#158
0$
#159
b1011 !
b1011 (
1$
#160
0$
#161
b1100 !
b1100 (
1$
#162
0$
#163
b1101 !
b1101 (
1$
#164
0$
#165
b1110 !
b1110 (
1$
#166
0$
#167
b1111 !
b1111 (
1$
#168
0$
#169
b10000 !
b10000 (
1$
#170
0$
#171
b10001 !
b10001 (
1$
#172
0$
#173
b10010 !
b10010 (
1$
#174
0$
#175
b10011 !
b10011 (
1$
#176
0$
#177
b10100 !
b10100 (
1$
#178
0$
#179
b10101 !
b10101 (
1$
#180
0$
#181
b10110 !
b10110 (
1$
#182
0$
#183
b10111 !
b10111 (
1$
#184
0$
#185
b11000 !
b11000 (
1$
#186
0$
#187
b11001 !
b11001 (
1$
#188
0$
#189
b11010 !
b11010 (
1$
#190
0$
#191
b11011 !
b11011 (
1$
#192
0$
#193
b11100 !
b11100 (
1$
#194
0$
#195
b11101 !
b11101 (
1$
#196
0$
#197
b11110 !
b11110 (
1$
#198
0$
#199
b11111 !
b11111 (
1$
#200
0$
#201
b100000 !
b100000 (
1$
#202
0$
#203
b100001 !
b100001 (
1$
#204
0$
#205
b100010 !
b100010 (
1$
#206
0$
#207
b100011 !
b100011 (
1$
#208
0$
#209
b100100 !
b100100 (
1$
#210
0$
#211
b100101 !
b100101 (
1$
#212
0$
#213
b100110 !
b100110 (
1$
#214
0$
#215
b100111 !
b100111 (
1$
#216
0$
#217
b101000 !
b101000 (
1$
#218
0$
#219
b101001 !
b101001 (
1$
#220
0$
#221
b101010 !
b101010 (
1$
#222
0$
#223
b101011 !
b101011 (
1$
#224
0$
#225
b101100 !
b101100 (
1$
#226
0$
#227
b101101 !
b101101 (
1$
#228
0$
#229
b101110 !
b101110 (
1$
#230
0$
#231
b101111 !
b101111 (
1$
#232
0$
#233
b110000 !
b110000 (
1$
#234
0$
#235
b110001 !
b110001 (
1$
#236
0$
#237
b110010 !
b110010 (
1$
#238
0$
#239
b110011 !
b110011 (
1$
#240
0$
#241
b110100 !
b110100 (
1$
#242
0$
#243
b110101 !
b110101 (
1$
#244
0$
#245
b110110 !
b110110 (
1$
#246
0$
#247
b110111 !
b110111 (
1$
#248
0$
#249
b111000 !
b111000 (
1$
#250
0$
#251
b111001 !
b111001 (
1$
#252
0$
#253
b111010 !
b111010 (
1$
#254
0$
#255
b111011 !
b111011 (
1$
#256
0$
#257
b10 "
b10 '
b0 !
b0 (
1$
#258
0$
#259
b1 !
b1 (
1$
#260
0$
#261
b10 !
b10 (
1$
#262
0$
#263
b11 !
b11 (
1$
#264
0$
#265
b100 !
b100 (
1$
#266
0$
#267
b101 !
b101 (
1$
#268
0$
#269
b110 !
b110 (
1$
#270
0$
#271
b111 !
b111 (
1$
#272
0$
#273
b1000 !
b1000 (
1$
#274
0$
#275
b1001 !
b1001 (
1$
#276
0$
#277
b1010 !
b1010 (
1$
#278
0$
#279
b1011 !
b1011 (
1$
#280
0$
#281
b1100 !
b1100 (
1$
#282
0$
#283
b1101 !
b1101 (
1$
#284
0$
#285
b1110 !
b1110 (
1$
#286
0$
#287
b1111 !
b1111 (
1$
#288
0$
#289
b10000 !
b10000 (
1$
#290
0$
#291
b10001 !
b10001 (
1$
#292
0$
#293
b10010 !
b10010 (
1$
#294
0$
#295
b10011 !
b10011 (
1$
#296
0$
#297
b10100 !
b10100 (
1$
#298
0$
#299
b10101 !
b10101 (
1$
#300
0$
#301
b10110 !
b10110 (
1$
#302
0$
#303
b10111 !
b10111 (
1$
#304
0$
#305
b11000 !
b11000 (
1$
#306
0$
#307
b11001 !
b11001 (
1$
#308
0$
#309
b11010 !
b11010 (
1$
#310
0$
#311
b11011 !
b11011 (
1$
#312
0$
#313
b11100 !
b11100 (
1$
#314
0$
#315
b11101 !
b11101 (
1$
#316
0$
#317
b11110 !
b11110 (
1$
#318
0$
#319
b11111 !
b11111 (
1$
#320
0$
#321
b100000 !
b100000 (
1$
#322
0$
#323
b100001 !
b100001 (
1$
#324
0$
#325
b100010 !
b100010 (
1$
#326
0$
#327
b100011 !
b100011 (
1$
#328
0$
#329
b100100 !
b100100 (
1$
#330
0$
#331
b100101 !
b100101 (
1$
#332
0$
#333
b100110 !
b100110 (
1$
#334
0$
#335
b100111 !
b100111 (
1$
#336
0$
#337
b101000 !
b101000 (
1$
#338
0$
#339
b101001 !
b101001 (
1$
#340
0$
#341
b101010 !
b101010 (
1$
#342
0$
#343
b101011 !
b101011 (
1$
#344
0$
#345
b101100 !
b101100 (
1$
#346
0$
#347
b101101 !
b101101 (
1$
#348
0$
#349
b101110 !
b101110 (
1$
#350
0$
#351
b101111 !
b101111 (
1$
#352
0$
#353
b110000 !
b110000 (
1$
#354
0$
#355
b110001 !
b110001 (
1$
#356
0$
#357
b110010 !
b110010 (
1$
#358
0$
#359
b110011 !
b110011 (
1$
#360
0$
#361
b110100 !
b110100 (
1$
#362
0$
#363
b110101 !
b110101 (
1$
#364
0$
#365
b110110 !
b110110 (
1$
#366
0$
#367
b110111 !
b110111 (
1$
#368
0$
#369
b111000 !
b111000 (
1$
#370
0$
#371
b111001 !
b111001 (
1$
#372
0$
#373
b111010 !
b111010 (
1$
#374
0$
#375
b111011 !
b111011 (
1$
#376
0$
#377
b11 "
b11 '
b0 !
b0 (
1$
#378
0$
#379
b1 !
b1 (
1$
#380
0$
#381
b10 !
b10 (
1$
#382
0$
#383
b11 !
b11 (
1$
#384
0$
#385
b100 !
b100 (
1$
#386
0$
#387
b101 !
b101 (
1$
#388
0$
#389
b110 !
b110 (
1$
#390
0$
#391
b111 !
b111 (
1$
#392
0$
#393
b1000 !
b1000 (
1$
#394
0$
#395
b1001 !
b1001 (
1$
#396
0$
#397
b1010 !
b1010 (
1$
#398
0$
#399
b1011 !
b1011 (
1$
#400
0$
#401
b1100 !
b1100 (
1$
#402
0$
#403
b1101 !
b1101 (
1$
#404
0$
#405
b1110 !
b1110 (
1$
#406
0$
#407
b1111 !
b1111 (
1$
#408
0$
#409
b10000 !
b10000 (
1$
#410
0$
#411
b10001 !
b10001 (
1$
#412
0$
#413
b10010 !
b10010 (
1$
#414
0$
#415
b10011 !
b10011 (
1$
#416
0$
#417
b10100 !
b10100 (
1$
#418
0$
#419
b10101 !
b10101 (
1$
#420
0$
#421
b10110 !
b10110 (
1$
#422
0$
#423
b10111 !
b10111 (
1$
#424
0$
#425
b11000 !
b11000 (
1$
#426
0$
#427
b11001 !
b11001 (
1$
#428
0$
#429
b11010 !
b11010 (
1$
#430
0$
#431
b11011 !
b11011 (
1$
#432
0$
#433
b11100 !
b11100 (
1$
#434
0$
#435
b11101 !
b11101 (
1$
#436
0$
#437
b11110 !
b11110 (
1$
#438
0$
#439
b11111 !
b11111 (
1$
#440
0$
#441
b100000 !
b100000 (
1$
#442
0$
#443
b100001 !
b100001 (
1$
#444
0$
#445
b100010 !
b100010 (
1$
#446
0$
#447
b100011 !
b100011 (
1$
#448
0$
#449
b100100 !
b100100 (
1$
#450
0$
#451
b100101 !
b100101 (
1$
#452
0$
#453
b100110 !
b100110 (
1$
#454
0$
#455
b100111 !
b100111 (
1$
#456
0$
#457
b101000 !
b101000 (
1$
#458
0$
#459
b101001 !
b101001 (
1$
#460
0$
#461
b101010 !
b101010 (
1$
#462
0$
#463
b101011 !
b101011 (
1$
#464
0$
#465
b101100 !
b101100 (
1$
#466
0$
#467
b101101 !
b101101 (
1$
#468
0$
#469
b101110 !
b101110 (
1$
#470
0$
#471
b101111 !
b101111 (
1$
#472
0$
#473
b110000 !
b110000 (
1$
#474
0$
#475
b110001 !
b110001 (
1$
#476
0$
#477
b110010 !
b110010 (
1$
#478
0$
#479
b110011 !
b110011 (
1$
#480
0$
#481
b110100 !
b110100 (
1$
#482
0$
#483
b110101 !
b110101 (
1$
#484
0$
#485
b110110 !
b110110 (
1$
#486
0$
#487
b110111 !
b110111 (
1$
#488
0$
#489
b111000 !
b111000 (
1$
#490
0$
#491
b111001 !
b111001 (
1$
#492
0$
#493
b111010 !
b111010 (
1$
#494
0$
#495
b111011 !
b111011 (
1$
#496
0$
#497
b100 "
b100 '
b0 !
b0 (
1$
#498
0$
#499
b1 !
b1 (
1$
#500
0$
#501
b10 !
b10 (
1$
#502
0$
#503
b11 !
b11 (
1$
#504
0$
#505
b100 !
b100 (
1$
#506
0$
#507
b101 !
b101 (
1$
#508
0$
#509
b110 !
b110 (
1$
#510
0$
#511
b111 !
b111 (
1$
#512
0$
#513
b1000 !
b1000 (
1$
#514
0$
#515
b1001 !
b1001 (
1$
#516
0$
#517
b1010 !
b1010 (
1$
#518
0$
#519
b1011 !
b1011 (
1$
#520
0$
#521
b1100 !
b1100 (
1$
#522
0$
#523
b1101 !
b1101 (
1$
#524
0$
#525
b1110 !
b1110 (
1$
#526
0$
#527
b1111 !
b1111 (
1$
#528
0$
#529
b10000 !
b10000 (
1$
#530
0$
#531
b10001 !
b10001 (
1$
#532
0$
#533
b10010 !
b10010 (
1$
#534
0$
#535
b10011 !
b10011 (
1$
#536
0$
#537
b10100 !
b10100 (
1$
#538
0$
#539
b10101 !
b10101 (
1$
#540
0$
#541
b10110 !
b10110 (
1$
#542
0$
#543
b10111 !
b10111 (
1$
#544
0$
#545
b11000 !
b11000 (
1$
#546
0$
#547
b11001 !
b11001 (
1$
#548
0$
#549
b11010 !
b11010 (
1$
#550
0$
#551
b11011 !
b11011 (
1$
#552
0$
#553
b11100 !
b11100 (
1$
#554
0$
#555
b11101 !
b11101 (
1$
#556
0$
#557
b11110 !
b11110 (
1$
#558
0$
#559
b11111 !
b11111 (
1$
#560
0$
#561
b100000 !
b100000 (
1$
#562
0$
#563
b100001 !
b100001 (
1$
#564
0$
#565
b100010 !
b100010 (
1$
#566
0$
#567
b100011 !
b100011 (
1$
#568
0$
#569
b100100 !
b100100 (
1$
#570
0$
#571
b100101 !
b100101 (
1$
#572
0$
#573
b100110 !
b100110 (
1$
#574
0$
#575
b100111 !
b100111 (
1$
#576
0$
#577
b101000 !
b101000 (
1$
#578
0$
#579
b101001 !
b101001 (
1$
#580
0$
#581
b101010 !
b101010 (
1$
#582
0$
#583
b101011 !
b101011 (
1$
#584
0$
#585
b101100 !
b101100 (
1$
#586
0$
#587
b101101 !
b101101 (
1$
#588
0$
#589
b101110 !
b101110 (
1$
#590
0$
#591
b101111 !
b101111 (
1$
#592
0$
#593
b110000 !
b110000 (
1$
#594
0$
#595
b110001 !
b110001 (
1$
#596
0$
#597
b110010 !
b110010 (
1$
#598
0$
#599
b110011 !
b110011 (
1$
#600
0$
#601
b110100 !
b110100 (
1$
#602
0$
#603
b110101 !
b110101 (
1$
#604
0$
#605
b110110 !
b110110 (
1$
#606
0$
#607
b110111 !
b110111 (
1$
#608
0$
#609
b111000 !
b111000 (
1$
#610
0$
#611
b111001 !
b111001 (
1$
#612
0$
#613
b111010 !
b111010 (
1$
#614
0$
#615
b111011 !
b111011 (
1$
#616
0$
#617
b101 "
b101 '
b0 !
b0 (
1$
#618
0$
#619
b1 !
b1 (
1$
#620
0$
#621
b10 !
b10 (
1$
#622
0$
#623
b11 !
b11 (
1$
#624
0$
#625
b100 !
b100 (
1$
#626
0$
#627
b101 !
b101 (
1$
#628
0$
#629
b110 !
b110 (
1$
#630
0$
#631
b111 !
b111 (
1$
#632
0$
#633
b1000 !
b1000 (
1$
#634
0$
#635
b1001 !
b1001 (
1$
#636
0$
#637
b1010 !
b1010 (
1$
#638
0$
#639
b1011 !
b1011 (
1$
#640
0$
#641
b1100 !
b1100 (
1$
#642
0$
#643
b1101 !
b1101 (
1$
#644
0$
#645
b1110 !
b1110 (
1$
#646
0$
#647
b1111 !
b1111 (
1$
#648
0$
#649
b10000 !
b10000 (
1$
#650
0$
#651
b10001 !
b10001 (
1$
#652
0$
#653
b10010 !
b10010 (
1$
#654
0$
#655
b10011 !
b10011 (
1$
#656
0$
#657
b10100 !
b10100 (
1$
#658
0$
#659
b10101 !
b10101 (
1$
#660
0$
#661
b10110 !
b10110 (
1$
#662
0$
#663
b10111 !
b10111 (
1$
#664
0$
#665
b11000 !
b11000 (
1$
#666
0$
#667
b11001 !
b11001 (
1$
#668
0$
#669
b11010 !
b11010 (
1$
#670
0$
#671
b11011 !
b11011 (
1$
#672
0$
#673
b11100 !
b11100 (
1$
#674
0$
#675
b11101 !
b11101 (
1$
#676
0$
#677
b11110 !
b11110 (
1$
#678
0$
#679
b11111 !
b11111 (
1$
#680
0$
#681
b100000 !
b100000 (
1$
#682
0$
#683
b100001 !
b100001 (
1$
#684
0$
#685
b100010 !
b100010 (
1$
#686
0$
#687
b100011 !
b100011 (
1$
#688
0$
#689
b100100 !
b100100 (
1$
#690
0$
#691
b100101 !
b100101 (
1$
#692
0$
#693
b100110 !
b100110 (
1$
#694
0$
#695
b100111 !
b100111 (
1$
#696
0$
#697
b101000 !
b101000 (
1$
#698
0$
#699
b101001 !
b101001 (
1$
#700
0$
#701
b101010 !
b101010 (
1$
#702
0$
#703
b101011 !
b101011 (
1$
#704
0$
#705
b101100 !
b101100 (
1$
#706
0$
#707
b101101 !
b101101 (
1$
#708
0$
#709
b101110 !
b101110 (
1$
#710
0$
#711
b101111 !
b101111 (
1$
#712
0$
#713
b110000 !
b110000 (
1$
#714
0$
#715
b110001 !
b110001 (
1$
#716
0$
#717
b110010 !
b110010 (
1$
#718
0$
#719
b110011 !
b110011 (
1$
#720
0$
#721
b110100 !
b110100 (
1$
#722
0$
#723
b110101 !
b110101 (
1$
#724
0$
#725
b110110 !
b110110 (
1$
#726
0$
#727
b110111 !
b110111 (
1$
#728
0$
#729
b111000 !
b111000 (
1$
#730
0$
#731
b111001 !
b111001 (
1$
#732
0$
#733
b111010 !
b111010 (
1$
#734
0$
#735
b111011 !
b111011 (
1$
#736
0$
#737
b110 "
b110 '
b0 !
b0 (
1$
#738
0$
#739
b1 !
b1 (
1$
#740
0$
#741
b10 !
b10 (
1$
#742
0$
#743
b11 !
b11 (
1$
#744
0$
#745
b100 !
b100 (
1$
#746
0$
#747
b101 !
b101 (
1$
#748
0$
#749
b110 !
b110 (
1$
#750
0$
#751
b111 !
b111 (
1$
#752
0$
#753
b1000 !
b1000 (
1$
#754
0$
#755
b1001 !
b1001 (
1$
#756
0$
#757
b1010 !
b1010 (
1$
#758
0$
#759
b1011 !
b1011 (
1$
#760
0$
#761
b1100 !
b1100 (
1$
#762
0$
#763
b1101 !
b1101 (
1$
#764
0$
#765
b1110 !
b1110 (
1$
#766
0$
#767
b1111 !
b1111 (
1$
#768
0$
#769
b10000 !
b10000 (
1$
#770
0$
#771
b10001 !
b10001 (
1$
#772
0$
#773
b10010 !
b10010 (
1$
#774
0$
#775
b10011 !
b10011 (
1$
#776
0$
#777
b10100 !
b10100 (
1$
#778
0$
#779
b10101 !
b10101 (
1$
#780
0$
#781
b10110 !
b10110 (
1$
#782
0$
#783
b10111 !
b10111 (
1$
#784
0$
#785
b11000 !
b11000 (
1$
#786
0$
#787
b11001 !
b11001 (
1$
#788
0$
#789
b11010 !
b11010 (
1$
#790
0$
#791
b11011 !
b11011 (
1$
#792
0$
#793
b11100 !
b11100 (
1$
#794
0$
#795
b11101 !
b11101 (
1$
#796
0$
#797
b11110 !
b11110 (
1$
#798
0$
#799
b11111 !
b11111 (
1$
#800
0$
#801
b100000 !
b100000 (
1$
#802
0$
#803
b100001 !
b100001 (
1$
#804
0$
#805
b100010 !
b100010 (
1$
#806
0$
#807
b100011 !
b100011 (
1$
#808
0$
#809
b100100 !
b100100 (
1$
#810
0$
#811
b100101 !
b100101 (
1$
#812
0$
#813
b100110 !
b100110 (
1$
#814
0$
#815
b100111 !
b100111 (
1$
#816
0$
#817
b101000 !
b101000 (
1$
#818
0$
#819
b101001 !
b101001 (
1$
#820
0$
#821
b101010 !
b101010 (
1$
#822
0$
#823
b101011 !
b101011 (
1$
#824
0$
#825
b101100 !
b101100 (
1$
#826
0$
#827
b101101 !
b101101 (
1$
#828
0$
#829
b101110 !
b101110 (
1$
#830
0$
#831
b101111 !
b101111 (
1$
#832
0$
#833
b110000 !
b110000 (
1$
#834
0$
#835
b110001 !
b110001 (
1$
#836
0$
#837
b110010 !
b110010 (
1$
#838
0$
#839
b110011 !
b110011 (
1$
#840
0$
#841
b110100 !
b110100 (
1$
#842
0$
#843
b110101 !
b110101 (
1$
#844
0$
#845
b110110 !
b110110 (
1$
#846
0$
#847
b110111 !
b110111 (
1$
#848
0$
#849
b111000 !
b111000 (
1$
#850
0$
#851
b111001 !
b111001 (
1$
#852
0$
#853
b111010 !
b111010 (
1$
#854
0$
#855
b111011 !
b111011 (
1$
#856
0$
#857
b111 "
b111 '
b0 !
b0 (
1$
#858
0$
#859
b1 !
b1 (
1$
#860
0$
#861
b10 !
b10 (
1$
#862
0$
#863
b11 !
b11 (
1$
#864
0$
#865
b100 !
b100 (
1$
#866
0$
#867
b101 !
b101 (
1$
#868
0$
#869
b110 !
b110 (
1$
#870
0$
#871
b111 !
b111 (
1$
#872
0$
#873
b1000 !
b1000 (
1$
#874
0$
#875
b1001 !
b1001 (
1$
#876
0$
#877
b1010 !
b1010 (
1$
#878
0$
#879
b1011 !
b1011 (
1$
#880
0$
#881
b1100 !
b1100 (
1$
#882
0$
#883
b1101 !
b1101 (
1$
#884
0$
#885
b1110 !
b1110 (
1$
#886
0$
#887
b1111 !
b1111 (
1$
#888
0$
#889
b10000 !
b10000 (
1$
#890
0$
#891
b10001 !
b10001 (
1$
#892
0$
#893
b10010 !
b10010 (
1$
#894
0$
#895
b10011 !
b10011 (
1$
#896
0$
#897
b10100 !
b10100 (
1$
#898
0$
#899
b10101 !
b10101 (
1$
#900
0$
#901
b10110 !
b10110 (
1$
#902
0$
#903
b10111 !
b10111 (
1$
#904
0$
#905
b11000 !
b11000 (
1$
#906
0$
#907
b11001 !
b11001 (
1$
#908
0$
#909
b11010 !
b11010 (
1$
#910
0$
#911
b11011 !
b11011 (
1$
#912
0$
#913
b11100 !
b11100 (
1$
#914
0$
#915
b11101 !
b11101 (
1$
#916
0$
#917
b11110 !
b11110 (
1$
#918
0$
#919
b11111 !
b11111 (
1$
#920
0$
#921
b100000 !
b100000 (
1$
#922
0$
#923
b100001 !
b100001 (
1$
#924
0$
#925
b100010 !
b100010 (
1$
#926
0$
#927
b100011 !
b100011 (
1$
#928
0$
#929
b100100 !
b100100 (
1$
#930
0$
#931
b100101 !
b100101 (
1$
#932
0$
#933
b100110 !
b100110 (
1$
#934
0$
#935
b100111 !
b100111 (
1$
#936
0$
#937
b101000 !
b101000 (
1$
#938
0$
#939
b101001 !
b101001 (
1$
#940
0$
#941
b101010 !
b101010 (
1$
#942
0$
#943
b101011 !
b101011 (
1$
#944
0$
#945
b101100 !
b101100 (
1$
#946
0$
#947
b101101 !
b101101 (
1$
#948
0$
#949
b101110 !
b101110 (
1$
#950
0$
#951
b101111 !
b101111 (
1$
#952
0$
#953
b110000 !
b110000 (
1$
#954
0$
#955
b110001 !
b110001 (
1$
#956
0$
#957
b110010 !
b110010 (
1$
#958
0$
#959
b110011 !
b110011 (
1$
#960
0$
#961
b110100 !
b110100 (
1$
#962
0$
#963
b110101 !
b110101 (
1$
#964
0$
#965
b110110 !
b110110 (
1$
#966
0$
#967
b110111 !
b110111 (
1$
#968
0$
#969
b111000 !
b111000 (
1$
#970
0$
#971
b111001 !
b111001 (
1$
#972
0$
#973
b111010 !
b111010 (
1$
#974
0$
#975
b111011 !
b111011 (
1$
#976
0$
#977
b1000 "
b1000 '
b0 !
b0 (
1$
#978
0$
#979
b1 !
b1 (
1$
#980
0$
#981
b10 !
b10 (
1$
#982
0$
#983
b11 !
b11 (
1$
#984
0$
#985
b100 !
b100 (
1$
#986
0$
#987
b101 !
b101 (
1$
#988
0$
#989
b110 !
b110 (
1$
#990
0$
#991
b111 !
b111 (
1$
#992
0$
#993
b1000 !
b1000 (
1$
#994
0$
#995
b1001 !
b1001 (
1$
#996
0$
#997
b1010 !
b1010 (
1$
#998
0$
#999
b1011 !
b1011 (
1$
#1000
0$
#1001
b1100 !
b1100 (
1$
#1002
0$
#1003
b1101 !
b1101 (
1$
#1004
0$
#1005
b1110 !
b1110 (
1$
#1006
0$
#1007
b1111 !
b1111 (
1$
#1008
0$
#1009
b10000 !
b10000 (
1$
#1010
0$
#1011
b10001 !
b10001 (
1$
#1012
0$
#1013
b10010 !
b10010 (
1$
#1014
0$
#1015
b10011 !
b10011 (
1$
#1016
0$
#1017
b10100 !
b10100 (
1$
#1018
0$
#1019
b10101 !
b10101 (
1$
#1020
0$
#1021
b10110 !
b10110 (
1$
#1022
0$
#1023
b10111 !
b10111 (
1$
#1024
0$
#1025
b11000 !
b11000 (
1$
#1026
0$
#1027
b11001 !
b11001 (
1$
#1028
0$
#1029
b11010 !
b11010 (
1$
#1030
0$
#1031
b11011 !
b11011 (
1$
#1032
0$
#1033
b11100 !
b11100 (
1$
#1034
0$
#1035
b11101 !
b11101 (
1$
#1036
0$
#1037
b11110 !
b11110 (
1$
#1038
0$
#1039
b11111 !
b11111 (
1$
#1040
0$
#1041
b100000 !
b100000 (
1$
#1042
0$
#1043
b100001 !
b100001 (
1$
#1044
0$
#1045
b100010 !
b100010 (
1$
#1046
0$
#1047
b100011 !
b100011 (
1$
#1048
0$
#1049
b100100 !
b100100 (
1$
#1050
0$
#1051
b100101 !
b100101 (
1$
#1052
0$
#1053
b100110 !
b100110 (
1$
#1054
0$
#1055
b100111 !
b100111 (
1$
#1056
0$
#1057
b101000 !
b101000 (
1$
#1058
0$
#1059
b101001 !
b101001 (
1$
#1060
0$
#1061
b101010 !
b101010 (
1$
#1062
0$
#1063
b101011 !
b101011 (
1$
#1064
0$
#1065
b101100 !
b101100 (
1$
#1066
0$
#1067
b101101 !
b101101 (
1$
#1068
0$
#1069
b101110 !
b101110 (
1$
#1070
0$
#1071
b101111 !
b101111 (
1$
#1072
0$
#1073
b110000 !
b110000 (
1$
#1074
0$
#1075
b110001 !
b110001 (
1$
#1076
0$
#1077
b110010 !
b110010 (
1$
#1078
0$
#1079
b110011 !
b110011 (
1$
#1080
0$
#1081
b110100 !
b110100 (
1$
#1082
0$
#1083
b110101 !
b110101 (
1$
#1084
0$
#1085
b110110 !
b110110 (
1$
#1086
0$
#1087
b110111 !
b110111 (
1$
#1088
0$
#1089
b111000 !
b111000 (
1$
#1090
0$
#1091
b111001 !
b111001 (
1$
#1092
0$
#1093
b111010 !
b111010 (
1$
#1094
0$
#1095
b111011 !
b111011 (
1$
#1096
0$
#1097
b1001 "
b1001 '
b0 !
b0 (
1$
#1098
0$
#1099
b1 !
b1 (
1$
#1100
0$
#1101
b10 !
b10 (
1$
#1102
0$
#1103
b11 !
b11 (
1$
#1104
0$
#1105
b100 !
b100 (
1$
#1106
0$
#1107
b101 !
b101 (
1$
#1108
0$
#1109
b110 !
b110 (
1$
#1110
0$
#1111
b111 !
b111 (
1$
#1112
0$
#1113
b1000 !
b1000 (
1$
#1114
0$
#1115
b1001 !
b1001 (
1$
#1116
0$
#1117
b1010 !
b1010 (
1$
#1118
0$
#1119
b1011 !
b1011 (
1$
#1120
0$
#1121
b1100 !
b1100 (
1$
#1122
0$
#1123
b1101 !
b1101 (
1$
#1124
0$
#1125
b1110 !
b1110 (
1$
#1126
0$
#1127
b1111 !
b1111 (
1$
#1128
0$
#1129
b10000 !
b10000 (
1$
#1130
0$
#1131
b10001 !
b10001 (
1$
#1132
0$
#1133
b10010 !
b10010 (
1$
#1134
0$
#1135
b10011 !
b10011 (
1$
#1136
0$
#1137
b10100 !
b10100 (
1$
#1138
0$
#1139
b10101 !
b10101 (
1$
#1140
0$
#1141
b10110 !
b10110 (
1$
#1142
0$
#1143
b10111 !
b10111 (
1$
#1144
0$
#1145
b11000 !
b11000 (
1$
#1146
0$
#1147
b11001 !
b11001 (
1$
#1148
0$
#1149
b11010 !
b11010 (
1$
#1150
0$
#1151
b11011 !
b11011 (
1$
#1152
0$
#1153
b11100 !
b11100 (
1$
#1154
0$
#1155
b11101 !
b11101 (
1$
#1156
0$
#1157
b11110 !
b11110 (
1$
#1158
0$
#1159
b11111 !
b11111 (
1$
#1160
0$
#1161
b100000 !
b100000 (
1$
#1162
0$
#1163
b100001 !
b100001 (
1$
#1164
0$
#1165
b100010 !
b100010 (
1$
#1166
0$
#1167
b100011 !
b100011 (
1$
#1168
0$
#1169
b100100 !
b100100 (
1$
#1170
0$
#1171
b100101 !
b100101 (
1$
#1172
0$
#1173
b100110 !
b100110 (
1$
#1174
0$
#1175
b100111 !
b100111 (
1$
#1176
0$
#1177
b101000 !
b101000 (
1$
#1178
0$
